ampache.py
ampache-6.9.0.dist-info/licenses/LICENSE
ampache-6.9.0.dist-info/METADATA
ampache-6.9.0.dist-info/WHEEL
ampache-6.9.0.dist-info/top_level.txt
ampache-6.9.0.dist-info/RECORD
