Metadata-Version: 2.4
Name: ampache
Version: 6.9.0
Summary: Python library for Ampache XML & JSON API
Home-page: https://github.com/ampache/python3-ampache
Download-URL: https://github.com/ampache/python3-ampache
Author: Lachlan de Waard (lachlan-00)
Author-email: lachlan.00@gmail.com
License: GPL-3.0
Classifier: Development Status :: 5 - Production/Stable
Classifier: License :: OSI Approved :: GNU General Public License v3 (GPLv3)
Classifier: Operating System :: POSIX :: Linux
Classifier: Operating System :: Microsoft :: Windows
Classifier: Programming Language :: Python :: 3
Classifier: Topic :: Software Development :: Libraries :: PHP Classes
Classifier: Intended Audience :: Developers
License-File: LICENSE
Dynamic: author
Dynamic: author-email
Dynamic: classifier
Dynamic: description
Dynamic: download-url
Dynamic: home-page
Dynamic: keywords
Dynamic: license
Dynamic: license-file
Dynamic: summary
